LICENSE
license-poetry-poems
poetry_poems/__init__.py
poetry_poems/cli.py
poetry_poems/core.py
poetry_poems/environment.py
poetry_poems/picker/__init__.py
poetry_poems/picker/colors.py
poetry_poems/picker/elements.py
poetry_poems/picker/keys.py
poetry_poems/poetry.py
poetry_poems/utils.py
poetry_poems-0.2.2.dist-info/entry_points.txt
poetry_poems-0.2.2.dist-info/LICENSE
poetry_poems-0.2.2.dist-info/WHEEL
poetry_poems-0.2.2.dist-info/METADATA
poetry_poems-0.2.2.dist-info/RECORD
