Metadata-Version: 2.1
Name: poetry-poems
Version: 0.2.2
Summary: Poetry Environments Switcher: CLI Tool to help manage Poetry Enviroments and corresponding Project Directories.
Home-page: https://poetry-poems.readthedocs.io/en/latest/
License: LGPL-3.0
Keywords: poetry,virtual environment,cli
Author: harper25
Author-email: olesjakubb@gmail.com
Requires-Python: >=3.6,<4.0
Classifier: Environment :: Console
Classifier: Environment :: Console :: Curses
Classifier: Intended Audience :: Developers
Classifier: License :: OSI Approved :: GNU Lesser General Public License v3 (LGPLv3)
Classifier: Operating System :: OS Independent
Classifier: Programming Language :: Python :: 3
Classifier: Programming Language :: Python :: 3.10
Classifier: Programming Language :: Python :: 3.6
Classifier: Programming Language :: Python :: 3.7
Classifier: Programming Language :: Python :: 3.8
Classifier: Programming Language :: Python :: 3.9
Classifier: Topic :: Software Development :: Libraries :: Python Modules
Requires-Dist: click (>=7.1.2,<8.0.0)
Requires-Dist: windows-curses (>=2.1.0,<3.0.0); sys_platform == "win32"
Project-URL: Repository, https://github.com/harper25/poetry-poems
